fuel_plugin_builder/__init__.py
fuel_plugin_builder/cli.py
fuel_plugin_builder/consts.py
fuel_plugin_builder/errors.py
fuel_plugin_builder/logger.py
fuel_plugin_builder/messages.py
fuel_plugin_builder/utils.py
fuel_plugin_builder/version_mapping.py
fuel_plugin_builder/actions/__init__.py
fuel_plugin_builder/actions/base.py
fuel_plugin_builder/actions/build.py
fuel_plugin_builder/actions/create.py
fuel_plugin_builder/templates/base/.gitignore
fuel_plugin_builder/templates/base/LICENSE
fuel_plugin_builder/templates/base/README.md.mako
fuel_plugin_builder/templates/base/environment_config.yaml.mako
fuel_plugin_builder/templates/base/pre_build_hook
fuel_plugin_builder/templates/base/deployment_scripts/deploy.sh.mako
fuel_plugin_builder/templates/base/repositories/centos/.gitkeep
fuel_plugin_builder/templates/base/repositories/ubuntu/.gitkeep
fuel_plugin_builder/templates/v1/metadata.yaml.mako
fuel_plugin_builder/templates/v1/tasks.yaml
fuel_plugin_builder/templates/v1/build/Release.mako
fuel_plugin_builder/templates/v2/build/plugin_rpm.spec.mako
fuel_plugin_builder/templates/v2/plugin_data/metadata.yaml.mako
fuel_plugin_builder/templates/v2/plugin_data/tasks.yaml
fuel_plugin_builder/templates/v3/build/plugin_rpm.spec.mako
fuel_plugin_builder/templates/v3/plugin_data/deployment_tasks.yaml.mako
fuel_plugin_builder/templates/v3/plugin_data/metadata.yaml.mako
fuel_plugin_builder/templates/v3/plugin_data/network_roles.yaml
fuel_plugin_builder/templates/v3/plugin_data/node_roles.yaml.mako
fuel_plugin_builder/templates/v3/plugin_data/volumes.yaml.mako
fuel_plugin_builder/templates/v4/plugin_data/components.yaml.mako
fuel_plugin_builder/templates/v4/plugin_data/deployment_tasks.yaml.mako
fuel_plugin_builder/templates/v4/plugin_data/environment_config.yaml.mako
fuel_plugin_builder/templates/v4/plugin_data/metadata.yaml.mako
fuel_plugin_builder/templates/v4/plugin_data/node_roles.yaml.mako
fuel_plugin_builder-4.2.0.dist-info/DESCRIPTION.rst
fuel_plugin_builder-4.2.0.dist-info/METADATA
fuel_plugin_builder-4.2.0.dist-info/RECORD
fuel_plugin_builder-4.2.0.dist-info/WHEEL
fuel_plugin_builder-4.2.0.dist-info/entry_points.txt
fuel_plugin_builder-4.2.0.dist-info/metadata.json
fuel_plugin_builder-4.2.0.dist-info/pbr.json
fuel_plugin_builder-4.2.0.dist-info/top_level.txt
