Metadata-Version: 2.0
Name: fuel-plugin-builder
Version: 4.2.0
Summary: Helps to create and build fuel plugins
Home-page: https://wiki.openstack.org/wiki/Fuel/Plugins
Author: OpenStack
Author-email: openstack-dev@lists.openstack.org
License: UNKNOWN
Platform: UNKNOWN
Classifier: Environment :: OpenStack
Classifier: Intended Audience :: Information Technology
Classifier: Intended Audience :: Developers
Classifier: License :: OSI Approved :: Apache Software License
Classifier: Operating System :: POSIX :: Linux
Classifier: Programming Language :: Python
Classifier: Programming Language :: Python :: 2
Classifier: Programming Language :: Python :: 2.7
Classifier: Topic :: System :: Software Distribution
Requires-Dist: Mako (==0.9.1)
Requires-Dist: PyYAML (==3.10)
Requires-Dist: jsonschema (==2.4.0)
Requires-Dist: pbr (>=1.6)
Requires-Dist: six (>=1.5.2)
